napari_3d_registration/__init__.py
napari_3d_registration/_widget.py
napari_3d_registration/napari.yaml
napari_3d_registration/_tests/__init__.py
napari_3d_registration/_tests/test_widget.py
napari_3d_registration-0.2.1.dist-info/licenses/LICENSE
napari_3d_registration-0.2.1.dist-info/METADATA
napari_3d_registration-0.2.1.dist-info/WHEEL
napari_3d_registration-0.2.1.dist-info/entry_points.txt
napari_3d_registration-0.2.1.dist-info/top_level.txt
napari_3d_registration-0.2.1.dist-info/RECORD
