Metadata-Version: 2.4
Name: napari-3D-registration
Version: 0.2.1
Summary: A plugin to help registering fluorescent movies in space and time
Home-page: https://github.com/GuignardLab/napari-3D-registration
Author: Leo Guignard
Author-email: leo.guignard@univ-amu.fr
License: MIT
Project-URL: Bug Tracker, https://github.com/GuignardLab/napari-3D-registration/issues
Project-URL: Documentation, https://github.com/GuignardLab/napari-3D-registration#README.md
Project-URL: Source Code, https://github.com/GuignardLab/napari-3D-registration
Project-URL: User Support, https://github.com/GuignardLab/napari-3D-registration/issues
Classifier: Development Status :: 2 - Pre-Alpha
Classifier: Framework :: napari
Classifier: Intended Audience :: Developers
Classifier: License :: OSI Approved :: MIT License
Classifier: Operating System :: OS Independent
Classifier: Programming Language :: Python
Classifier: Programming Language :: Python :: 3
Classifier: Programming Language :: Python :: 3 :: Only
Classifier: Programming Language :: Python :: 3.8
Classifier: Programming Language :: Python :: 3.9
Classifier: Programming Language :: Python :: 3.10
Classifier: Topic :: Scientific/Engineering :: Image Processing
Requires-Python: >=3.8
License-File: LICENSE
Requires-Dist: numpy
Requires-Dist: magicgui
Requires-Dist: qtpy
Requires-Dist: 3D-registration
Provides-Extra: testing
Requires-Dist: tox; extra == "testing"
Requires-Dist: pytest; extra == "testing"
Requires-Dist: pytest-cov; extra == "testing"
Requires-Dist: pytest-qt; extra == "testing"
Requires-Dist: napari; extra == "testing"
Requires-Dist: pyqt5; extra == "testing"
Dynamic: license-file
